{
  "connection": "default",
  "collectionName": "categories",
  "info": {
    "name": "category",
    "description": "Product category"
  },
  "options": {
    "increments": true,
    "timestamps": true,
    "comment": ""
  },
  "attributes": {
    "Nombre": {
      "required": true,
      "type": "string"
    },
    "Price": {
      "type": "decimal"
    },
    "Color": {
      "enum": [
        "Blue",
        "Red",
        "Green",
        "Yellow",
        "Grey",
        "Pink",
        "Lightblue",
        "Black",
        "White"
      ],
      "type": "enumeration"
    },
    "Size": {
      "enum": [
        "XS",
        "S",
        "M",
        "L",
        "XL",
        "XXL",
        "XXXL"
      ],
      "type": "enumeration"
    },
    "Degree": {
      "enum": [
        "Telecomunicacion",
        "Biomedica",
        "Datos"
      ],
      "type": "enumeration"
    },
    "Model": {
      "enum": [
        "a",
        "b",
        "c",
        "d"
      ],
      "type": "enumeration"
    }
  }
}